[{"title": "Minecraft Launcher", "path": "c:\\Users\\chasz\\Downloads\\Programs\\PYTHON\\Game_launcher\\games\\Minecraft Launcher.lnk", "cover": "https://cdn2.steamgriddb.com/grid/5f3fcb29f750d4489f5a235f1a0dfadc.png", "hero": "https://cdn2.steamgriddb.com/hero/22a2a45564a22009dc0856afba6c4be1.png"}, {"title": "Fortnite", "path": "c:\\Users\\chasz\\Downloads\\Programs\\PYTHON\\Game_launcher\\games\\Fortnite.lnk", "cover": "https://cdn2.steamgriddb.com/grid/6c4d541fc68d426aa028bc05f38164d1.png", "hero": "https://cdn2.steamgriddb.com/hero/33e4954478a4c91de8be3b9feb28e972.png"}, {"title": "Sea of Thieves", "path": "c:\\Users\\chasz\\Downloads\\Programs\\PYTHON\\Game_launcher\\games\\Sea of Thieves.lnk", "cover": "https://cdn2.steamgriddb.com/grid/fc28dd210d52ecb0135730aa1d151b1b.png", "hero": "https://cdn2.steamgriddb.com/hero/889fbd1aec443cef389ea10c93b498d8.jpg"}, {"title": "Ready or Not", "path": "c:\\Users\\chasz\\Downloads\\Programs\\PYTHON\\Game_launcher\\games\\Ready or Not.lnk", "cover": "https://cdn2.steamgriddb.com/grid/06206ba97d1ba310284651649f66a546.png", "hero": "https://cdn2.steamgriddb.com/hero/f7f7eddc6c81fa096ae87e0ba025499a.png"}, {"title": "inZOI", "path": "c:\\Users\\chasz\\Downloads\\Programs\\PYTHON\\Game_launcher\\games\\inZOI.url", "cover": "https://cdn2.steamgriddb.com/grid/c1706d2e74396f97b0aa6f09d90643e8.png", "hero": "https://cdn2.steamgriddb.com/hero/31bea61e20f7b9d2519eca8a7adc82c0.png"}, {"title": "BeamNG.drive", "path": "c:\\Users\\chasz\\Downloads\\Programs\\PYTHON\\Game_launcher\\games\\BeamNG.drive.url", "cover": "https://cdn2.steamgriddb.com/grid/56b98caabdcf92d58337e4ccff7f7a4e.png", "hero": "https://cdn2.steamgriddb.com/hero/beab831c783550ad003eddaed2d0849d.png"}, {"title": "Cities Skylines II", "path": "c:\\Users\\chasz\\Downloads\\Programs\\PYTHON\\Game_launcher\\games\\Cities Skylines II.url", "cover": "https://cdn2.steamgriddb.com/grid/b550b09e83026f8a11a0354dfc503974.png", "hero": "https://cdn2.steamgriddb.com/hero/c9236859f1c5404b0138f97bbb9b128d.png"}, {"title": "Grand Theft Auto IV The Complete Edition", "path": "c:\\Users\\chasz\\Downloads\\Programs\\PYTHON\\Game_launcher\\games\\Grand Theft Auto IV The Complete Edition.url", "cover": "https://cdn2.steamgriddb.com/grid/a32bc8141e168ff20fdfe3f0fbc72155.png", "hero": "https://cdn2.steamgriddb.com/hero/ed58966527f3896422f854dc5d703513.png"}]